{
  "$schema": "https://turborepo.com/schema.json",
  "ui": "tui",
  "tasks": {
    "build": {
      "dependsOn": ["^build"],
      "inputs": ["$TURBO_DEFAULT$", ".env*"],
      "outputs": [".next/**", "!.next/cache/**"],
      "env": [
        "CONVEX_DEPLOYMENT",
        "NEXT_PUBLIC_CONVEX_URL",
        "NEXT_PUBLIC_CLERK_PUBLISHABLE_KEY",
        "CLERK_SECRET_KEY",
        "NEXT_PUBLIC_CLERK_SIGN_UP_URL",
        "NEXT_PUBLIC_CLERK_SIGN_UP_FALLBACK_REDIRECT_URL",
        "NEXT_PUBLIC_CLERK_SIGN_IN_FALLBACK_REDIRECT_URL",
        "IMAGEKIT_PRIVATE_KEY",
        "IMAGEKIT_PUBLIC_KEY",
        "IMAGEKIT_URL_ENDPOINT",
        "NEXT_PUBLIC_POSTHOG_KEY",
        "NEXT_PUBLIC_POSTHOG_HOST",
        "RESEND_API_KEY",
        "CLERK_JWT_ISSUER_DOMAIN",
        "NODE_ENV",
        "CLERK_SIGN_IN_URL",
        "CLERK_SIGN_UP_URL",
        "RAZORPAY_KEY_SECRET",
        "RAZORPAY_KEY_ID"
      ]
    },
    "lint": {
      "dependsOn": ["^lint"]
    },
    "check-types": {
      "dependsOn": ["^check-types"]
    },
    "dev": {
      "cache": false,
      "persistent": true
    }
  }
}
